pyantv/__init__.py
pyantv/_version.py
pyantv/globals.py
pyantv/types.py
pyantv/charts/__init__.py
pyantv/charts/base.py
pyantv/charts/chart.py
pyantv/charts/mixins.py
pyantv/charts/basic_charts/__init__.py
pyantv/charts/basic_charts/area.py
pyantv/charts/basic_charts/box.py
pyantv/charts/basic_charts/boxplot.py
pyantv/charts/basic_charts/cell.py
pyantv/charts/basic_charts/chord.py
pyantv/charts/basic_charts/density.py
pyantv/charts/basic_charts/force_graph.py
pyantv/charts/basic_charts/gauge.py
pyantv/charts/basic_charts/geo_path.py
pyantv/charts/basic_charts/heatmap.py
pyantv/charts/basic_charts/image.py
pyantv/charts/basic_charts/interval.py
pyantv/charts/basic_charts/line.py
pyantv/charts/basic_charts/link.py
pyantv/charts/basic_charts/liquid.py
pyantv/charts/basic_charts/pack.py
pyantv/charts/basic_charts/point.py
pyantv/charts/basic_charts/polygon.py
pyantv/charts/basic_charts/range.py
pyantv/charts/basic_charts/rect.py
pyantv/charts/basic_charts/sankey.py
pyantv/charts/basic_charts/shape.py
pyantv/charts/basic_charts/text.py
pyantv/charts/basic_charts/tree.py
pyantv/charts/basic_charts/treemap.py
pyantv/charts/basic_charts/vector.py
pyantv/charts/basic_charts/wordcloud.py
pyantv/charts/composition_charts/__init__.py
pyantv/charts/composition_charts/facet_circle.py
pyantv/charts/composition_charts/facet_rect.py
pyantv/charts/composition_charts/geo_view.py
pyantv/charts/composition_charts/repeat_matrix.py
pyantv/charts/composition_charts/space_flex.py
pyantv/charts/composition_charts/space_layer.py
pyantv/charts/composition_charts/timing_key_frame.py
pyantv/charts/composition_charts/view.py
pyantv/commons/__init__.py
pyantv/commons/utils.py
pyantv/datasets/__init__.py
pyantv/datasets/filename.json
pyantv/options/__init__.py
pyantv/options/chart_options.py
pyantv/options/global_options.py
pyantv/options/series_options.py
pyantv/render/__init__.py
pyantv/render/display.py
pyantv/render/engine.py
pyantv/render/templates/macro
pyantv-0.1.0.dist-info/LICENSE
pyantv-0.1.0.dist-info/METADATA
pyantv-0.1.0.dist-info/WHEEL
pyantv-0.1.0.dist-info/top_level.txt
pyantv-0.1.0.dist-info/RECORD
