Metadata-Version: 2.2
Name: pyantv
Version: 0.1.0
Summary: python visualization sdk for AntV
Home-page: https://github.com/sunhailin-Leo/pyantv
Author: sunhailin-Leo
Author-email: shjkfld379978424@gmail.com
License: MIT
Keywords: AntV,charts,plotting-tool
Classifier: Development Status :: 5 - Production/Stable
Classifier: Environment :: Console
Classifier: Intended Audience :: Developers
Classifier: License :: OSI Approved :: MIT License
Classifier: Operating System :: OS Independent
Classifier: Programming Language :: Python
Classifier: Programming Language :: Python :: 3.6
Classifier: Programming Language :: Python :: 3.7
Classifier: Programming Language :: Python :: 3.8
Classifier: Programming Language :: Python :: 3.9
Classifier: Programming Language :: Python :: 3.10
Classifier: Programming Language :: Python :: 3.11
Classifier: Programming Language :: Python :: 3.12
Classifier: Programming Language :: Python :: 3.13
Classifier: Topic :: Software Development :: Libraries
License-File: LICENSE
Requires-Dist: setuptools>=38.3
Requires-Dist: jinja2>=2.11.3
Requires-Dist: simplejson
Dynamic: author
Dynamic: author-email
Dynamic: classifier
Dynamic: home-page
Dynamic: keywords
Dynamic: license
Dynamic: requires-dist
Dynamic: summary
